[
    {
        "history": [
            {
                "user": "帮我接通张三的语音通话，再帮我搜索出好友电话并用联通卡打电话给他",
                "state": "启动社交应用程序通话(联系人=张三, 通话模式=语音通话, 应用名称=None) AND 查找联系人(联系人=None) THEN 打电话(设备类型=None, 电话卡=联通卡, 电话号码=[ToFill], 联系人=None)",
                "assistant": "为您成功接通张三的语音通话，您需要查的好友电话是哪位好友呢"
            },
            {
                "user": "李四",
                "state": "查找联系人(联系人=李四) THEN 打电话(设备类型=None, 电话卡=联通卡, 电话号码=[ToFill], 联系人=李四)",
                "assistant": null
            }
        ]
    },
    {
        "history": [
            {
                "user": "帮我给王五打一个语音通话，之后再查找一下号码并用我的电信卡打电话给他",
                "state": "启动社交应用程序通话(联系人=王五, 通话模式=语音通话, 应用名称=None) AND 查找联系人(联系人=None) THEN 打电话(设备类型=None, 电话卡=电信卡, 电话号码=[ToFill], 联系人=None)",
                "assistant": "为您成功拨打王五的语音通话，帮您搜索电话号码的好友是谁呢"
            },
            {
                "user": "赵六",
                "state": "查找联系人(联系人=赵六) THEN 打电话(设备类型=None, 电话卡=电信卡, 电话号码=[ToFill], 联系人=赵六)",
                "assistant": null
            }
        ]
    },
    {
        "history": [
            {
                "user": "帮我接通小红的语音通话，搜索出好友电话并用移动卡打电话给这位好友",
                "state": "启动社交应用程序通话(联系人=小红, 通话模式=语音通话, 应用名称=None) AND 查找联系人(联系人=None) THEN 打电话(设备类型=None, 电话卡=移动卡, 电话号码=[ToFill], 联系人=None)",
                "assistant": "为您成功接通小红的语音通话，您需要查的好友电话是哪位好友呢"
            },
            {
                "user": "小明",
                "state": "查找联系人(联系人=小明) THEN 打电话(设备类型=None, 电话卡=移动卡, 电话号码=[ToFill], 联系人=小明)",
                "assistant": null
            }
        ]
    },
    {
        "history": [
            {
                "user": "请帮我接通一下小刚的语音通话，接听之后再查找一下号码并打给他用我的电信卡",
                "state": "启动社交应用程序通话(联系人=小刚, 通话模式=语音通话, 应用名称=None) AND 查找联系人(联系人=None) THEN 打电话(设备类型=None, 电话卡=电信卡, 电话号码=[ToFill], 联系人=None)",
                "assistant": "为您成功接通一下小刚的语音通话，帮您搜索哪位好友的电话号码呢"
            },
            {
                "user": "小丽",
                "state": "查找联系人(联系人=小丽) THEN 打电话(设备类型=None, 电话卡=电信卡, 电话号码=[ToFill], 联系人=小丽)",
                "assistant": null
            }
        ]
    },
    {
        "history": [
            {
                "user": "帮我接通小芳的语音通话，帮我搜索电话并用移动卡打电话给她",
                "state": "启动社交应用程序通话(联系人=小芳, 通话模式=语音通话, 应用名称=None) AND 查找联系人(联系人=None) THEN 打电话(设备类型=None, 电话卡=移动卡, 电话号码=[ToFill], 联系人=None)",
                "assistant": "成功接通小芳的语音通话，您需要查找哪位好友电话呢"
            },
            {
                "user": "小强",
                "state": "查找联系人(联系人=小强) THEN 打电话(设备类型=None, 电话卡=移动卡, 电话号码=[ToFill], 联系人=小强)",
                "assistant": null
            }
        ]
    },
    {
        "history": [
            {
                "user": "帮我接通小美的语音通话，再帮我搜索出好友电话并用联通卡打电话给她",
                "state": "启动社交应用程序通话(联系人=小美, 通话模式=语音通话, 应用名称=None) AND 查找联系人(联系人=None) THEN 打电话(设备类型=None, 电话卡=联通卡, 电话号码=[ToFill], 联系人=None)",
                "assistant": "为您成功接通小美的语音通话，您需要查的好友电话是哪位好友呢"
            },
            {
                "user": "小华",
                "state": "查找联系人(联系人=小华) THEN 打电话(设备类型=None, 电话卡=联通卡, 电话号码=[ToFill], 联系人=小华)",
                "assistant": null
            }
        ]
    },
    {
        "history": [
            {
                "user": "帮我给小杰打一个语音通话，之后再查找一下号码并用我的电信卡打电话给他",
                "state": "启动社交应用程序通话(联系人=小杰, 通话模式=语音通话, 应用名称=None) AND 查找联系人(联系人=None) THEN 打电话(设备类型=None, 电话卡=电信卡, 电话号码=[ToFill], 联系人=None)",
                "assistant": "为您成功拨打小杰的语音通话，帮您搜索电话号码的好友是谁呢"
            },
            {
                "user": "小丽",
                "state": "查找联系人(联系人=小丽) THEN 打电话(设备类型=None, 电话卡=电信卡, 电话号码=[ToFill], 联系人=小丽)",
                "assistant": null
            }
        ]
    },
    {
        "history": [
            {
                "user": "帮我接通小丽的语音通话，搜索出好友电话并用移动卡打电话给这位好友",
                "state": "启动社交应用程序通话(联系人=小丽, 通话模式=语音通话, 应用名称=None) AND 查找联系人(联系人=None) THEN 打电话(设备类型=None, 电话卡=移动卡, 电话号码=[ToFill], 联系人=None)",
                "assistant": "为您成功接通小丽的语音通话，您需要查的好友电话是哪位好友呢"
            },
            {
                "user": "小明",
                "state": "查找联系人(联系人=小明) THEN 打电话(设备类型=None, 电话卡=移动卡, 电话号码=[ToFill], 联系人=小明)",
                "assistant": null
            }
        ]
    },
    {
        "history": [
            {
                "user": "请帮我接通一下小强的语音通话，接听之后再查找一下号码并打给他用我的电信卡",
                "state": "启动社交应用程序通话(联系人=小强, 通话模式=语音通话, 应用名称=None) AND 查找联系人(联系人=None) THEN 打电话(设备类型=None, 电话卡=电信卡, 电话号码=[ToFill], 联系人=None)",
                "assistant": "为您成功接通一下小强的语音通话，帮您搜索哪位好友的电话号码呢"
            },
            {
                "user": "小芳",
                "state": "查找联系人(联系人=小芳) THEN 打电话(设备类型=None, 电话卡=电信卡, 电话号码=[ToFill], 联系人=小芳)",
                "assistant": null
            }
        ]
    },
    {
        "history": [
            {
                "user": "帮我接通小明的语音通话，帮我搜索电话并用移动卡打电话给她",
                "state": "启动社交应用程序通话(联系人=小明, 通话模式=语音通话, 应用名称=None) AND 查找联系人(联系人=None) THEN 打电话(设备类型=None, 电话卡=移动卡, 电话号码=[ToFill], 联系人=None)",
                "assistant": "成功接通小明的语音通话，您需要查找哪位好友电话呢"
            },
            {
                "user": "小丽",
                "state": "查找联系人(联系人=小丽) THEN 打电话(设备类型=None, 电话卡=移动卡, 电话号码=[ToFill], 联系人=小丽)",
                "assistant": null
            }
        ]
    },
    {
        "history": [
            {
                "user": "帮我接通小明的视频通话，然后查找一下他的电话号码并用联通卡打给他",
                "state": "启动社交应用程序通话(联系人=小明, 通话模式=视频通话, 应用名称=None) AND 查找联系人(联系人=None) THEN 打电话(设备类型=None, 电话卡=联通卡, 电话号码=[ToFill], 联系人=None)",
                "assistant": "为您成功接通小明的视频通话，您需要查找哪位好友的电话号码呢"
            },
            {
                "user": "小红",
                "state": "查找联系人(联系人=小红) THEN 打电话(设备类型=None, 电话卡=联通卡, 电话号码=[ToFill], 联系人=小红)",
                "assistant": null
            }
        ]
    },
    {
        "history": [
            {
                "user": "请帮我接通小王的语音通话，接听之后再查找一下号码并打给他用我的电信卡",
                "state": "启动社交应用程序通话(联系人=小王, 通话模式=语音通话, 应用名称=None) AND 查找联系人(联系人=None) THEN 打电话(设备类型=None, 电话卡=电信卡, 电话号码=[ToFill], 联系人=None)",
                "assistant": "为您成功接通小王的语音通话，帮您搜索哪位好友的电话号码呢"
            },
            {
                "user": "小李",
                "state": "查找联系人(联系人=小李) THEN 打电话(设备类型=None, 电话卡=电信卡, 电话号码=[ToFill], 联系人=小李)",
                "assistant": null
            }
        ]
    },
    {
        "history": [
            {
                "user": "帮我接通小张的视频通话，然后查找一下他的电话号码并用移动卡打给他",
                "state": "启动社交应用程序通话(联系人=小张, 通话模式=视频通话, 应用名称=None) AND 查找联系人(联系人=None) THEN 打电话(设备类型=None, 电话卡=移动卡, 电话号码=[ToFill], 联系人=None)",
                "assistant": "为您成功接通小张的视频通话，您需要查找哪位好友的电话号码呢"
            },
            {
                "user": "小刘",
                "state": "查找联系人(联系人=小刘) THEN 打电话(设备类型=None, 电话卡=移动卡, 电话号码=[ToFill], 联系人=小刘)",
                "assistant": null
            }
        ]
    },
    {
        "history": [
            {
                "user": "请帮我接通小赵的语音通话，接听之后再查找一下号码并打给他用我的联通卡",
                "state": "启动社交应用程序通话(联系人=小赵, 通话模式=语音通话, 应用名称=None) AND 查找联系人(联系人=None) THEN 打电话(设备类型=None, 电话卡=联通卡, 电话号码=[ToFill], 联系人=None)",
                "assistant": "为您成功接通小赵的语音通话，帮您搜索哪位好友的电话号码呢"
            },
            {
                "user": "小孙",
                "state": "查找联系人(联系人=小孙) THEN 打电话(设备类型=None, 电话卡=联通卡, 电话号码=[ToFill], 联系人=小孙)",
                "assistant": null
            }
        ]
    },
    {
        "history": [
            {
                "user": "帮我接通小钱的视频通话，然后查找一下他的电话号码并用电信卡打给他",
                "state": "启动社交应用程序通话(联系人=小钱, 通话模式=视频通话, 应用名称=None) AND 查找联系人(联系人=None) THEN 打电话(设备类型=None, 电话卡=电信卡, 电话号码=[ToFill], 联系人=None)",
                "assistant": "为您成功接通小钱的视频通话，您需要查找哪位好友的电话号码呢"
            },
            {
                "user": "小周",
                "state": "查找联系人(联系人=小周) THEN 打电话(设备类型=None, 电话卡=电信卡, 电话号码=[ToFill], 联系人=小周)",
                "assistant": null
            }
        ]
    },
    {
        "history": [
            {
                "user": "请帮我接通小吴的语音通话，接听之后再查找一下号码并打给他用我的移动卡",
                "state": "启动社交应用程序通话(联系人=小吴, 通话模式=语音通话, 应用名称=None) AND 查找联系人(联系人=None) THEN 打电话(设备类型=None, 电话卡=移动卡, 电话号码=[ToFill], 联系人=None)",
                "assistant": "为您成功接通小吴的语音通话，帮您搜索哪位好友的电话号码呢"
            },
            {
                "user": "小郑",
                "state": "查找联系人(联系人=小郑) THEN 打电话(设备类型=None, 电话卡=移动卡, 电话号码=[ToFill], 联系人=小郑)",
                "assistant": null
            }
        ]
    },
    {
        "history": [
            {
                "user": "帮我接通小王的视频通话，然后查找一下他的电话号码并用联通卡打给他",
                "state": "启动社交应用程序通话(联系人=小王, 通话模式=视频通话, 应用名称=None) AND 查找联系人(联系人=None) THEN 打电话(设备类型=None, 电话卡=联通卡, 电话号码=[ToFill], 联系人=None)",
                "assistant": "为您成功接通小王的视频通话，您需要查找哪位好友的电话号码呢"
            },
            {
                "user": "小陈",
                "state": "查找联系人(联系人=小陈) THEN 打电话(设备类型=None, 电话卡=联通卡, 电话号码=[ToFill], 联系人=小陈)",
                "assistant": null
            }
        ]
    },
    {
        "history": [
            {
                "user": "请帮我接通小李的语音通话，接听之后再查找一下号码并打给他用我的电信卡",
                "state": "启动社交应用程序通话(联系人=小李, 通话模式=语音通话, 应用名称=None) AND 查找联系人(联系人=None) THEN 打电话(设备类型=None, 电话卡=电信卡, 电话号码=[ToFill], 联系人=None)",
                "assistant": "为您成功接通小李的语音通话，帮您搜索哪位好友的电话号码呢"
            },
            {
                "user": "小黄",
                "state": "查找联系人(联系人=小黄) THEN 打电话(设备类型=None, 电话卡=电信卡, 电话号码=[ToFill], 联系人=小黄)",
                "assistant": null
            }
        ]
    },
    {
        "history": [
            {
                "user": "帮我接通小张的视频通话，然后查找一下他的电话号码并用移动卡打给他",
                "state": "启动社交应用程序通话(联系人=小张, 通话模式=视频通话, 应用名称=None) AND 查找联系人(联系人=None) THEN 打电话(设备类型=None, 电话卡=移动卡, 电话号码=[ToFill], 联系人=None)",
                "assistant": "为您成功接通小张的视频通话，您需要查找哪位好友的电话号码呢"
            },
            {
                "user": "小林",
                "state": "查找联系人(联系人=小林) THEN 打电话(设备类型=None, 电话卡=移动卡, 电话号码=[ToFill], 联系人=小林)",
                "assistant": null
            }
        ]
    },
    {
        "history": [
            {
                "user": "请帮我接通小赵的语音通话，接听之后再查找一下号码并打给他用我的联通卡",
                "state": "启动社交应用程序通话(联系人=小赵, 通话模式=语音通话, 应用名称=None) AND 查找联系人(联系人=None) THEN 打电话(设备类型=None, 电话卡=联通卡, 电话号码=[ToFill], 联系人=None)",
                "assistant": "为您成功接通小赵的语音通话，帮您搜索哪位好友的电话号码呢"
            },
            {
                "user": "小杨",
                "state": "查找联系人(联系人=小杨) THEN 打电话(设备类型=None, 电话卡=联通卡, 电话号码=[ToFill], 联系人=小杨)",
                "assistant": null
            }
        ]
    },
    {
        "history": [
            {
                "user": "帮我接通小明的视频通话，再帮我搜索出好友电话并用联通卡打电话给他",
                "state": "启动社交应用程序通话(联系人=小明, 通话模式=视频通话, 应用名称=None) AND 查找联系人(联系人=None) THEN 打电话(设备类型=None, 电话卡=联通卡, 电话号码=[ToFill], 联系人=None)",
                "assistant": "为您成功接通小明的视频通话，您需要查的好友电话是哪位好友呢"
            },
            {
                "user": "张三",
                "state": "查找联系人(联系人=张三) THEN 打电话(设备类型=None, 电话卡=联通卡, 电话号码=[ToFill], 联系人=张三)",
                "assistant": null
            }
        ]
    },
    {
        "history": [
            {
                "user": "帮我给小红打一个视频通话，之后再查找一下号码并用我的电信卡打电话给她",
                "state": "启动社交应用程序通话(联系人=小红, 通话模式=视频通话, 应用名称=None) AND 查找联系人(联系人=None) THEN 打电话(设备类型=None, 电话卡=电信卡, 电话号码=[ToFill], 联系人=None)",
                "assistant": "为您成功拨打小红的视频通话，帮您搜索电话号码的好友是谁呢"
            },
            {
                "user": "李四",
                "state": "查找联系人(联系人=李四) THEN 打电话(设备类型=None, 电话卡=电信卡, 电话号码=[ToFill], 联系人=李四)",
                "assistant": null
            }
        ]
    },
    {
        "history": [
            {
                "user": "帮我接通小王的语音通话，搜索出好友电话并用联通卡打电话给这位好友",
                "state": "启动社交应用程序通话(联系人=小王, 通话模式=语音通话, 应用名称=None) AND 查找联系人(联系人=None) THEN 打电话(设备类型=None, 电话卡=联通卡, 电话号码=[ToFill], 联系人=None)",
                "assistant": "为您成功接通小王的语音通话，您需要查的好友电话是哪位好友呢"
            },
            {
                "user": "赵六",
                "state": "查找联系人(联系人=赵六) THEN 打电话(设备类型=None, 电话卡=联通卡, 电话号码=[ToFill], 联系人=赵六)",
                "assistant": null
            }
        ]
    },
    {
        "history": [
            {
                "user": "请帮我接通一下小李的视频通话，接听之后再查找一下号码并打给她用我的移动卡",
                "state": "启动社交应用程序通话(联系人=小李, 通话模式=视频通话, 应用名称=None) AND 查找联系人(联系人=None) THEN 打电话(设备类型=None, 电话卡=移动卡, 电话号码=[ToFill], 联系人=None)",
                "assistant": "为您成功接通一下小李的视频通话，帮您搜索哪位好友的电话号码呢"
            },
            {
                "user": "王五",
                "state": "查找联系人(联系人=王五) THEN 打电话(设备类型=None, 电话卡=移动卡, 电话号码=[ToFill], 联系人=王五)",
                "assistant": null
            }
        ]
    },
    {
        "history": [
            {
                "user": "帮我接通小张的语音通话，帮我搜索电话并用联通卡打电话给他",
                "state": "启动社交应用程序通话(联系人=小张, 通话模式=语音通话, 应用名称=None) AND 查找联系人(联系人=None) THEN 打电话(设备类型=None, 电话卡=联通卡, 电话号码=[ToFill], 联系人=None)",
                "assistant": "成功接通小张的语音通话，您需要查找哪位好友电话呢"
            },
            {
                "user": "孙七",
                "state": "查找联系人(联系人=孙七) THEN 打电话(设备类型=None, 电话卡=联通卡, 电话号码=[ToFill], 联系人=孙七)",
                "assistant": null
            }
        ]
    },
    {
        "history": [
            {
                "user": "帮我接通小刘的视频通话，再帮我搜索出好友电话并用电信卡打电话给他",
                "state": "启动社交应用程序通话(联系人=小刘, 通话模式=视频通话, 应用名称=None) AND 查找联系人(联系人=None) THEN 打电话(设备类型=None, 电话卡=电信卡, 电话号码=[ToFill], 联系人=None)",
                "assistant": "为您成功接通小刘的视频通话，您需要查的好友电话是哪位好友呢"
            },
            {
                "user": "周八",
                "state": "查找联系人(联系人=周八) THEN 打电话(设备类型=None, 电话卡=电信卡, 电话号码=[ToFill], 联系人=周八)",
                "assistant": null
            }
        ]
    },
    {
        "history": [
            {
                "user": "帮我给小陈打一个语音通话，之后再查找一下号码并用我的联通卡打电话给他",
                "state": "启动社交应用程序通话(联系人=小陈, 通话模式=语音通话, 应用名称=None) AND 查找联系人(联系人=None) THEN 打电话(设备类型=None, 电话卡=联通卡, 电话号码=[ToFill], 联系人=None)",
                "assistant": "为您成功拨打小陈的语音通话，帮您搜索电话号码的好友是谁呢"
            },
            {
                "user": "吴九",
                "state": "查找联系人(联系人=吴九) THEN 打电话(设备类型=None, 电话卡=联通卡, 电话号码=[ToFill], 联系人=吴九)",
                "assistant": null
            }
        ]
    },
    {
        "history": [
            {
                "user": "帮我接通小杨的语音通话，搜索出好友电话并用移动卡打电话给这位好友",
                "state": "启动社交应用程序通话(联系人=小杨, 通话模式=语音通话, 应用名称=None) AND 查找联系人(联系人=None) THEN 打电话(设备类型=None, 电话卡=移动卡, 电话号码=[ToFill], 联系人=None)",
                "assistant": "为您成功接通小杨的语音通话，您需要查的好友电话是哪位好友呢"
            },
            {
                "user": "郑十",
                "state": "查找联系人(联系人=郑十) THEN 打电话(设备类型=None, 电话卡=移动卡, 电话号码=[ToFill], 联系人=郑十)",
                "assistant": null
            }
        ]
    },
    {
        "history": [
            {
                "user": "请帮我接通一下小赵的视频通话，接听之后再查找一下号码并打给她用我的电信卡",
                "state": "启动社交应用程序通话(联系人=小赵, 通话模式=视频通话, 应用名称=None) AND 查找联系人(联系人=None) THEN 打电话(设备类型=None, 电话卡=电信卡, 电话号码=[ToFill], 联系人=None)",
                "assistant": "为您成功接通一下小赵的视频通话，帮您搜索哪位好友的电话号码呢"
            },
            {
                "user": "钱十一",
                "state": "查找联系人(联系人=钱十一) THEN 打电话(设备类型=None, 电话卡=电信卡, 电话号码=[ToFill], 联系人=钱十一)",
                "assistant": null
            }
        ]
    },
    {
        "history": [
            {
                "user": "帮我接通小孙的语音通话，帮我搜索电话并用联通卡打电话给他",
                "state": "启动社交应用程序通话(联系人=小孙, 通话模式=语音通话, 应用名称=None) AND 查找联系人(联系人=None) THEN 打电话(设备类型=None, 电话卡=联通卡, 电话号码=[ToFill], 联系人=None)",
                "assistant": "成功接通小孙的语音通话，您需要查找哪位好友电话呢"
            },
            {
                "user": "李十二",
                "state": "查找联系人(联系人=李十二) THEN 打电话(设备类型=None, 电话卡=联通卡, 电话号码=[ToFill], 联系人=李十二)",
                "assistant": null
            }
        ]
    },
    {
        "history": [
            {
                "user": "帮我接通张三的语音通话，再帮我搜索出好友电话并用联通卡打电话给他",
                "state": "启动社交应用程序通话(联系人=张三, 通话模式=语音通话, 应用名称=None) AND 查找联系人(联系人=None) THEN 打电话(设备类型=None, 电话卡=联通卡, 电话号码=[ToFill], 联系人=None)",
                "assistant": "为您成功接通张三的语音通话，您需要查的好友电话是哪位好友呢"
            },
            {
                "user": "李四",
                "state": "查找联系人(联系人=李四) THEN 打电话(设备类型=None, 电话卡=联通卡, 电话号码=[ToFill], 联系人=李四)",
                "assistant": null
            }
        ]
    },
    {
        "history": [
            {
                "user": "帮我给王五打一个语音通话，之后再查找一下号码并用我的电信卡打电话给他",
                "state": "启动社交应用程序通话(联系人=王五, 通话模式=语音通话, 应用名称=None) AND 查找联系人(联系人=None) THEN 打电话(设备类型=None, 电话卡=电信卡, 电话号码=[ToFill], 联系人=None)",
                "assistant": "为您成功拨打王五的语音通话，帮您搜索电话号码的好友是谁呢"
            },
            {
                "user": "赵六",
                "state": "查找联系人(联系人=赵六) THEN 打电话(设备类型=None, 电话卡=电信卡, 电话号码=[ToFill], 联系人=赵六)",
                "assistant": null
            }
        ]
    },
    {
        "history": [
            {
                "user": "帮我接通小红的语音通话，搜索出好友电话并用移动卡打电话给这位好友",
                "state": "启动社交应用程序通话(联系人=小红, 通话模式=语音通话, 应用名称=None) AND 查找联系人(联系人=None) THEN 打电话(设备类型=None, 电话卡=移动卡, 电话号码=[ToFill], 联系人=None)",
                "assistant": "为您成功接通小红的语音通话，您需要查的好友电话是哪位好友呢"
            },
            {
                "user": "小明",
                "state": "查找联系人(联系人=小明) THEN 打电话(设备类型=None, 电话卡=移动卡, 电话号码=[ToFill], 联系人=小明)",
                "assistant": null
            }
        ]
    },
    {
        "history": [
            {
                "user": "请帮我接通一下小刚的语音通话，接听之后再查找一下号码并打给他用我的电信卡",
                "state": "启动社交应用程序通话(联系人=小刚, 通话模式=语音通话, 应用名称=None) AND 查找联系人(联系人=None) THEN 打电话(设备类型=None, 电话卡=电信卡, 电话号码=[ToFill], 联系人=None)",
                "assistant": "为您成功接通一下小刚的语音通话，帮您搜索哪位好友的电话号码呢"
            },
            {
                "user": "小丽",
                "state": "查找联系人(联系人=小丽) THEN 打电话(设备类型=None, 电话卡=电信卡, 电话号码=[ToFill], 联系人=小丽)",
                "assistant": null
            }
        ]
    },
    {
        "history": [
            {
                "user": "帮我接通小芳的语音通话，帮我搜索电话并用移动卡打电话给她",
                "state": "启动社交应用程序通话(联系人=小芳, 通话模式=语音通话, 应用名称=None) AND 查找联系人(联系人=None) THEN 打电话(设备类型=None, 电话卡=移动卡, 电话号码=[ToFill], 联系人=None)",
                "assistant": "成功接通小芳的语音通话，您需要查找哪位好友电话呢"
            },
            {
                "user": "小强",
                "state": "查找联系人(联系人=小强) THEN 打电话(设备类型=None, 电话卡=移动卡, 电话号码=[ToFill], 联系人=小强)",
                "assistant": null
            }
        ]
    },
    {
        "history": [
            {
                "user": "帮我接通小美的语音通话，再帮我搜索出好友电话并用联通卡打电话给她",
                "state": "启动社交应用程序通话(联系人=小美, 通话模式=语音通话, 应用名称=None) AND 查找联系人(联系人=None) THEN 打电话(设备类型=None, 电话卡=联通卡, 电话号码=[ToFill], 联系人=None)",
                "assistant": "为您成功接通小美的语音通话，您需要查的好友电话是哪位好友呢"
            },
            {
                "user": "小华",
                "state": "查找联系人(联系人=小华) THEN 打电话(设备类型=None, 电话卡=联通卡, 电话号码=[ToFill], 联系人=小华)",
                "assistant": null
            }
        ]
    },
    {
        "history": [
            {
                "user": "帮我给小杰打一个语音通话，之后再查找一下号码并用我的电信卡打电话给他",
                "state": "启动社交应用程序通话(联系人=小杰, 通话模式=语音通话, 应用名称=None) AND 查找联系人(联系人=None) THEN 打电话(设备类型=None, 电话卡=电信卡, 电话号码=[ToFill], 联系人=None)",
                "assistant": "为您成功拨打小杰的语音通话，帮您搜索电话号码的好友是谁呢"
            },
            {
                "user": "小丽",
                "state": "查找联系人(联系人=小丽) THEN 打电话(设备类型=None, 电话卡=电信卡, 电话号码=[ToFill], 联系人=小丽)",
                "assistant": null
            }
        ]
    },
    {
        "history": [
            {
                "user": "帮我接通小丽的语音通话，搜索出好友电话并用移动卡打电话给这位好友",
                "state": "启动社交应用程序通话(联系人=小丽, 通话模式=语音通话, 应用名称=None) AND 查找联系人(联系人=None) THEN 打电话(设备类型=None, 电话卡=移动卡, 电话号码=[ToFill], 联系人=None)",
                "assistant": "为您成功接通小丽的语音通话，您需要查的好友电话是哪位好友呢"
            },
            {
                "user": "小明",
                "state": "查找联系人(联系人=小明) THEN 打电话(设备类型=None, 电话卡=移动卡, 电话号码=[ToFill], 联系人=小明)",
                "assistant": null
            }
        ]
    },
    {
        "history": [
            {
                "user": "请帮我接通一下小强的语音通话，接听之后再查找一下号码并打给他用我的电信卡",
                "state": "启动社交应用程序通话(联系人=小强, 通话模式=语音通话, 应用名称=None) AND 查找联系人(联系人=None) THEN 打电话(设备类型=None, 电话卡=电信卡, 电话号码=[ToFill], 联系人=None)",
                "assistant": "为您成功接通一下小强的语音通话，帮您搜索哪位好友的电话号码呢"
            },
            {
                "user": "小芳",
                "state": "查找联系人(联系人=小芳) THEN 打电话(设备类型=None, 电话卡=电信卡, 电话号码=[ToFill], 联系人=小芳)",
                "assistant": null
            }
        ]
    },
    {
        "history": [
            {
                "user": "帮我接通小华的语音通话，帮我搜索电话并用移动卡打电话给她",
                "state": "启动社交应用程序通话(联系人=小华, 通话模式=语音通话, 应用名称=None) AND 查找联系人(联系人=None) THEN 打电话(设备类型=None, 电话卡=移动卡, 电话号码=[ToFill], 联系人=None)",
                "assistant": "成功接通小华的语音通话，您需要查找哪位好友电话呢"
            },
            {
                "user": "小杰",
                "state": "查找联系人(联系人=小杰) THEN 打电话(设备类型=None, 电话卡=移动卡, 电话号码=[ToFill], 联系人=小杰)",
                "assistant": null
            }
        ]
    },
    {
        "history": [
            {
                "user": "帮我接通张三的语音通话，再帮我搜索出好友电话并用联通卡打电话给他",
                "state": "启动社交应用程序通话(联系人=张三, 通话模式=语音通话, 应用名称=None) AND 查找联系人(联系人=None) THEN 打电话(设备类型=None, 电话卡=联通卡, 电话号码=[ToFill], 联系人=None)",
                "assistant": "为您成功接通张三的语音通话，您需要查的好友电话是哪位好友呢"
            },
            {
                "user": "李四",
                "state": "查找联系人(联系人=李四) THEN 打电话(设备类型=None, 电话卡=联通卡, 电话号码=[ToFill], 联系人=李四)",
                "assistant": null
            }
        ]
    },
    {
        "history": [
            {
                "user": "帮我给王五打一个语音通话，之后再查找一下号码并用我的电信卡打电话给他",
                "state": "启动社交应用程序通话(联系人=王五, 通话模式=语音通话, 应用名称=None) AND 查找联系人(联系人=None) THEN 打电话(设备类型=None, 电话卡=电信卡, 电话号码=[ToFill], 联系人=None)",
                "assistant": "为您成功拨打王五的语音通话，帮您搜索电话号码的好友是谁呢"
            },
            {
                "user": "赵六",
                "state": "查找联系人(联系人=赵六) THEN 打电话(设备类型=None, 电话卡=电信卡, 电话号码=[ToFill], 联系人=赵六)",
                "assistant": null
            }
        ]
    },
    {
        "history": [
            {
                "user": "帮我接通小红的语音通话，搜索出好友电话并用移动卡打电话给这位好友",
                "state": "启动社交应用程序通话(联系人=小红, 通话模式=语音通话, 应用名称=None) AND 查找联系人(联系人=None) THEN 打电话(设备类型=None, 电话卡=移动卡, 电话号码=[ToFill], 联系人=None)",
                "assistant": "为您成功接通小红的语音通话，您需要查的好友电话是哪位好友呢"
            },
            {
                "user": "小明",
                "state": "查找联系人(联系人=小明) THEN 打电话(设备类型=None, 电话卡=移动卡, 电话号码=[ToFill], 联系人=小明)",
                "assistant": null
            }
        ]
    },
    {
        "history": [
            {
                "user": "请帮我接通一下小刚的语音通话，接听之后再查找一下号码并打给他用我的电信卡",
                "state": "启动社交应用程序通话(联系人=小刚, 通话模式=语音通话, 应用名称=None) AND 查找联系人(联系人=None) THEN 打电话(设备类型=None, 电话卡=电信卡, 电话号码=[ToFill], 联系人=None)",
                "assistant": "为您成功接通一下小刚的语音通话，帮您搜索哪位好友的电话号码呢"
            },
            {
                "user": "小丽",
                "state": "查找联系人(联系人=小丽) THEN 打电话(设备类型=None, 电话卡=电信卡, 电话号码=[ToFill], 联系人=小丽)",
                "assistant": null
            }
        ]
    },
    {
        "history": [
            {
                "user": "帮我接通小美的语音通话，帮我搜索电话并用移动卡打电话给她",
                "state": "启动社交应用程序通话(联系人=小美, 通话模式=语音通话, 应用名称=None) AND 查找联系人(联系人=None) THEN 打电话(设备类型=None, 电话卡=移动卡, 电话号码=[ToFill], 联系人=None)",
                "assistant": "成功接通小美的语音通话，您需要查找哪位好友电话呢"
            },
            {
                "user": "小强",
                "state": "查找联系人(联系人=小强) THEN 打电话(设备类型=None, 电话卡=移动卡, 电话号码=[ToFill], 联系人=小强)",
                "assistant": null
            }
        ]
    },
    {
        "history": [
            {
                "user": "帮我接通小李的语音通话，再帮我搜索出好友电话并用联通卡打电话给他",
                "state": "启动社交应用程序通话(联系人=小李, 通话模式=语音通话, 应用名称=None) AND 查找联系人(联系人=None) THEN 打电话(设备类型=None, 电话卡=联通卡, 电话号码=[ToFill], 联系人=None)",
                "assistant": "为您成功接通小李的语音通话，您需要查的好友电话是哪位好友呢"
            },
            {
                "user": "小王",
                "state": "查找联系人(联系人=小王) THEN 打电话(设备类型=None, 电话卡=联通卡, 电话号码=[ToFill], 联系人=小王)",
                "assistant": null
            }
        ]
    },
    {
        "history": [
            {
                "user": "帮我给小张打一个语音通话，之后再查找一下号码并用我的电信卡打电话给他",
                "state": "启动社交应用程序通话(联系人=小张, 通话模式=语音通话, 应用名称=None) AND 查找联系人(联系人=None) THEN 打电话(设备类型=None, 电话卡=电信卡, 电话号码=[ToFill], 联系人=None)",
                "assistant": "为您成功拨打小张的语音通话，帮您搜索电话号码的好友是谁呢"
            },
            {
                "user": "小赵",
                "state": "查找联系人(联系人=小赵) THEN 打电话(设备类型=None, 电话卡=电信卡, 电话号码=[ToFill], 联系人=小赵)",
                "assistant": null
            }
        ]
    },
    {
        "history": [
            {
                "user": "帮我接通小刘的语音通话，搜索出好友电话并用移动卡打电话给这位好友",
                "state": "启动社交应用程序通话(联系人=小刘, 通话模式=语音通话, 应用名称=None) AND 查找联系人(联系人=None) THEN 打电话(设备类型=None, 电话卡=移动卡, 电话号码=[ToFill], 联系人=None)",
                "assistant": "为您成功接通小刘的语音通话，您需要查的好友电话是哪位好友呢"
            },
            {
                "user": "小陈",
                "state": "查找联系人(联系人=小陈) THEN 打电话(设备类型=None, 电话卡=移动卡, 电话号码=[ToFill], 联系人=小陈)",
                "assistant": null
            }
        ]
    },
    {
        "history": [
            {
                "user": "请帮我接通一下小杨的语音通话，接听之后再查找一下号码并打给他用我的电信卡",
                "state": "启动社交应用程序通话(联系人=小杨, 通话模式=语音通话, 应用名称=None) AND 查找联系人(联系人=None) THEN 打电话(设备类型=None, 电话卡=电信卡, 电话号码=[ToFill], 联系人=None)",
                "assistant": "为您成功接通一下小杨的语音通话，帮您搜索哪位好友的电话号码呢"
            },
            {
                "user": "小吴",
                "state": "查找联系人(联系人=小吴) THEN 打电话(设备类型=None, 电话卡=电信卡, 电话号码=[ToFill], 联系人=小吴)",
                "assistant": null
            }
        ]
    },
    {
        "history": [
            {
                "user": "帮我接通小周的语音通话，帮我搜索电话并用移动卡打电话给她",
                "state": "启动社交应用程序通话(联系人=小周, 通话模式=语音通话, 应用名称=None) AND 查找联系人(联系人=None) THEN 打电话(设备类型=None, 电话卡=移动卡, 电话号码=[ToFill], 联系人=None)",
                "assistant": "成功接通小周的语音通话，您需要查找哪位好友电话呢"
            },
            {
                "user": "小郑",
                "state": "查找联系人(联系人=小郑) THEN 打电话(设备类型=None, 电话卡=移动卡, 电话号码=[ToFill], 联系人=小郑)",
                "assistant": null
            }
        ]
    },
    {
        "history": [
            {
                "user": "帮我接通张三的语音通话，再帮我搜索出好友电话并用联通卡打电话给他",
                "state": "启动社交应用程序通话(联系人=张三, 通话模式=语音通话, 应用名称=None) AND 查找联系人(联系人=None) THEN 打电话(设备类型=None, 电话卡=联通卡, 电话号码=[ToFill], 联系人=None)",
                "assistant": "为您成功接通张三的语音通话，您需要查的好友电话是哪位好友呢"
            },
            {
                "user": "李四",
                "state": "查找联系人(联系人=李四) THEN 打电话(设备类型=None, 电话卡=联通卡, 电话号码=[ToFill], 联系人=李四)",
                "assistant": null
            }
        ]
    },
    {
        "history": [
            {
                "user": "帮我给王五打一个视频通话，之后再查找一下号码并用我的电信卡打电话给他",
                "state": "启动社交应用程序通话(联系人=王五, 通话模式=视频通话, 应用名称=None) AND 查找联系人(联系人=None) THEN 打电话(设备类型=None, 电话卡=电信卡, 电话号码=[ToFill], 联系人=None)",
                "assistant": "为您成功拨打王五的视频通话，帮您搜索电话号码的好友是谁呢"
            },
            {
                "user": "赵六",
                "state": "查找联系人(联系人=赵六) THEN 打电话(设备类型=None, 电话卡=电信卡, 电话号码=[ToFill], 联系人=赵六)",
                "assistant": null
            }
        ]
    },
    {
        "history": [
            {
                "user": "帮我接通小红的语音通话，搜索出好友电话并用移动卡打电话给这位好友",
                "state": "启动社交应用程序通话(联系人=小红, 通话模式=语音通话, 应用名称=None) AND 查找联系人(联系人=None) THEN 打电话(设备类型=None, 电话卡=移动卡, 电话号码=[ToFill], 联系人=None)",
                "assistant": "为您成功接通小红的语音通话，您需要查的好友电话是哪位好友呢"
            },
            {
                "user": "小明",
                "state": "查找联系人(联系人=小明) THEN 打电话(设备类型=None, 电话卡=移动卡, 电话号码=[ToFill], 联系人=小明)",
                "assistant": null
            }
        ]
    },
    {
        "history": [
            {
                "user": "请帮我接通一下小李的视频通话，接听之后再查找一下号码并打给他用我的联通卡",
                "state": "启动社交应用程序通话(联系人=小李, 通话模式=视频通话, 应用名称=None) AND 查找联系人(联系人=None) THEN 打电话(设备类型=None, 电话卡=联通卡, 电话号码=[ToFill], 联系人=None)",
                "assistant": "为您成功接通一下小李的视频通话，帮您搜索哪位好友的电话号码呢"
            },
            {
                "user": "小张",
                "state": "查找联系人(联系人=小张) THEN 打电话(设备类型=None, 电话卡=联通卡, 电话号码=[ToFill], 联系人=小张)",
                "assistant": null
            }
        ]
    },
    {
        "history": [
            {
                "user": "帮我接通小王的语音通话，帮我搜索电话并用移动卡打电话给他",
                "state": "启动社交应用程序通话(联系人=小王, 通话模式=语音通话, 应用名称=None) AND 查找联系人(联系人=None) THEN 打电话(设备类型=None, 电话卡=移动卡, 电话号码=[ToFill], 联系人=None)",
                "assistant": "成功接通小王的语音通话，您需要查找哪位好友电话呢"
            },
            {
                "user": "小刘",
                "state": "查找联系人(联系人=小刘) THEN 打电话(设备类型=None, 电话卡=移动卡, 电话号码=[ToFill], 联系人=小刘)",
                "assistant": null
            }
        ]
    },
    {
        "history": [
            {
                "user": "帮我接通小陈的语音通话，再帮我搜索出好友电话并用电信卡打电话给他",
                "state": "启动社交应用程序通话(联系人=小陈, 通话模式=语音通话, 应用名称=None) AND 查找联系人(联系人=None) THEN 打电话(设备类型=None, 电话卡=电信卡, 电话号码=[ToFill], 联系人=None)",
                "assistant": "为您成功接通小陈的语音通话，您需要查的好友电话是哪位好友呢"
            },
            {
                "user": "小赵",
                "state": "查找联系人(联系人=小赵) THEN 打电话(设备类型=None, 电话卡=电信卡, 电话号码=[ToFill], 联系人=小赵)",
                "assistant": null
            }
        ]
    },
    {
        "history": [
            {
                "user": "帮我给小杨打一个视频通话，之后再查找一下号码并用我的移动卡打电话给他",
                "state": "启动社交应用程序通话(联系人=小杨, 通话模式=视频通话, 应用名称=None) AND 查找联系人(联系人=None) THEN 打电话(设备类型=None, 电话卡=移动卡, 电话号码=[ToFill], 联系人=None)",
                "assistant": "为您成功拨打小杨的视频通话，帮您搜索电话号码的好友是谁呢"
            },
            {
                "user": "小吴",
                "state": "查找联系人(联系人=小吴) THEN 打电话(设备类型=None, 电话卡=移动卡, 电话号码=[ToFill], 联系人=小吴)",
                "assistant": null
            }
        ]
    },
    {
        "history": [
            {
                "user": "帮我接通小周的语音通话，搜索出好友电话并用联通卡打电话给这位好友",
                "state": "启动社交应用程序通话(联系人=小周, 通话模式=语音通话, 应用名称=None) AND 查找联系人(联系人=None) THEN 打电话(设备类型=None, 电话卡=联通卡, 电话号码=[ToFill], 联系人=None)",
                "assistant": "为您成功接通小周的语音通话，您需要查的好友电话是哪位好友呢"
            },
            {
                "user": "小郑",
                "state": "查找联系人(联系人=小郑) THEN 打电话(设备类型=None, 电话卡=联通卡, 电话号码=[ToFill], 联系人=小郑)",
                "assistant": null
            }
        ]
    },
    {
        "history": [
            {
                "user": "请帮我接通一下小钱的视频通话，接听之后再查找一下号码并打给他用我的电信卡",
                "state": "启动社交应用程序通话(联系人=小钱, 通话模式=视频通话, 应用名称=None) AND 查找联系人(联系人=None) THEN 打电话(设备类型=None, 电话卡=电信卡, 电话号码=[ToFill], 联系人=None)",
                "assistant": "为您成功接通一下小钱的视频通话，帮您搜索哪位好友的电话号码呢"
            },
            {
                "user": "小孙",
                "state": "查找联系人(联系人=小孙) THEN 打电话(设备类型=None, 电话卡=电信卡, 电话号码=[ToFill], 联系人=小孙)",
                "assistant": null
            }
        ]
    },
    {
        "history": [
            {
                "user": "帮我接通小孙的语音通话，帮我搜索电话并用移动卡打电话给他",
                "state": "启动社交应用程序通话(联系人=小孙, 通话模式=语音通话, 应用名称=None) AND 查找联系人(联系人=None) THEN 打电话(设备类型=None, 电话卡=移动卡, 电话号码=[ToFill], 联系人=None)",
                "assistant": "成功接通小孙的语音通话，您需要查找哪位好友电话呢"
            },
            {
                "user": "小李",
                "state": "查找联系人(联系人=小李) THEN 打电话(设备类型=None, 电话卡=移动卡, 电话号码=[ToFill], 联系人=小李)",
                "assistant": null
            }
        ]
    },
    {
        "history": [
            {
                "user": "帮我接通张三的语音通话，再帮我搜索出好友电话并用联通卡打电话给他",
                "state": "启动社交应用程序通话(联系人=张三, 通话模式=语音通话, 应用名称=None) AND 查找联系人(联系人=None) THEN 打电话(设备类型=None, 电话卡=联通卡, 电话号码=[ToFill], 联系人=None)",
                "assistant": "为您成功接通张三的语音通话，您需要查的好友电话是哪位好友呢"
            },
            {
                "user": "李四",
                "state": "查找联系人(联系人=李四) THEN 打电话(设备类型=None, 电话卡=联通卡, 电话号码=[ToFill], 联系人=李四)",
                "assistant": null
            }
        ]
    },
    {
        "history": [
            {
                "user": "帮我给王五打一个语音通话，之后再查找一下号码并用我的电信卡打电话给他",
                "state": "启动社交应用程序通话(联系人=王五, 通话模式=语音通话, 应用名称=None) AND 查找联系人(联系人=None) THEN 打电话(设备类型=None, 电话卡=电信卡, 电话号码=[ToFill], 联系人=None)",
                "assistant": "为您成功拨打王五的语音通话，帮您搜索电话号码的好友是谁呢"
            },
            {
                "user": "赵六",
                "state": "查找联系人(联系人=赵六) THEN 打电话(设备类型=None, 电话卡=电信卡, 电话号码=[ToFill], 联系人=赵六)",
                "assistant": null
            }
        ]
    },
    {
        "history": [
            {
                "user": "帮我接通小红的语音通话，搜索出好友电话并用移动卡打电话给这位好友",
                "state": "启动社交应用程序通话(联系人=小红, 通话模式=语音通话, 应用名称=None) AND 查找联系人(联系人=None) THEN 打电话(设备类型=None, 电话卡=移动卡, 电话号码=[ToFill], 联系人=None)",
                "assistant": "为您成功接通小红的语音通话，您需要查的好友电话是哪位好友呢"
            },
            {
                "user": "小明",
                "state": "查找联系人(联系人=小明) THEN 打电话(设备类型=None, 电话卡=移动卡, 电话号码=[ToFill], 联系人=小明)",
                "assistant": null
            }
        ]
    },
    {
        "history": [
            {
                "user": "请帮我接通一下小刚的语音通话，接听之后再查找一下号码并打给他用我的电信卡",
                "state": "启动社交应用程序通话(联系人=小刚, 通话模式=语音通话, 应用名称=None) AND 查找联系人(联系人=None) THEN 打电话(设备类型=None, 电话卡=电信卡, 电话号码=[ToFill], 联系人=None)",
                "assistant": "为您成功接通一下小刚的语音通话，帮您搜索哪位好友的电话号码呢"
            },
            {
                "user": "小丽",
                "state": "查找联系人(联系人=小丽) THEN 打电话(设备类型=None, 电话卡=电信卡, 电话号码=[ToFill], 联系人=小丽)",
                "assistant": null
            }
        ]
    },
    {
        "history": [
            {
                "user": "帮我接通小芳的语音通话，帮我搜索电话并用移动卡打电话给她",
                "state": "启动社交应用程序通话(联系人=小芳, 通话模式=语音通话, 应用名称=None) AND 查找联系人(联系人=None) THEN 打电话(设备类型=None, 电话卡=移动卡, 电话号码=[ToFill], 联系人=None)",
                "assistant": "成功接通小芳的语音通话，您需要查找哪位好友电话呢"
            },
            {
                "user": "小强",
                "state": "查找联系人(联系人=小强) THEN 打电话(设备类型=None, 电话卡=移动卡, 电话号码=[ToFill], 联系人=小强)",
                "assistant": null
            }
        ]
    },
    {
        "history": [
            {
                "user": "帮我接通小美的语音通话，再帮我搜索出好友电话并用联通卡打电话给她",
                "state": "启动社交应用程序通话(联系人=小美, 通话模式=语音通话, 应用名称=None) AND 查找联系人(联系人=None) THEN 打电话(设备类型=None, 电话卡=联通卡, 电话号码=[ToFill], 联系人=None)",
                "assistant": "为您成功接通小美的语音通话，您需要查的好友电话是哪位好友呢"
            },
            {
                "user": "小华",
                "state": "查找联系人(联系人=小华) THEN 打电话(设备类型=None, 电话卡=联通卡, 电话号码=[ToFill], 联系人=小华)",
                "assistant": null
            }
        ]
    },
    {
        "history": [
            {
                "user": "帮我给小杰打一个语音通话，之后再查找一下号码并用我的电信卡打电话给他",
                "state": "启动社交应用程序通话(联系人=小杰, 通话模式=语音通话, 应用名称=None) AND 查找联系人(联系人=None) THEN 打电话(设备类型=None, 电话卡=电信卡, 电话号码=[ToFill], 联系人=None)",
                "assistant": "为您成功拨打小杰的语音通话，帮您搜索电话号码的好友是谁呢"
            },
            {
                "user": "小丽",
                "state": "查找联系人(联系人=小丽) THEN 打电话(设备类型=None, 电话卡=电信卡, 电话号码=[ToFill], 联系人=小丽)",
                "assistant": null
            }
        ]
    },
    {
        "history": [
            {
                "user": "帮我接通小丽的语音通话，搜索出好友电话并用移动卡打电话给这位好友",
                "state": "启动社交应用程序通话(联系人=小丽, 通话模式=语音通话, 应用名称=None) AND 查找联系人(联系人=None) THEN 打电话(设备类型=None, 电话卡=移动卡, 电话号码=[ToFill], 联系人=None)",
                "assistant": "为您成功接通小丽的语音通话，您需要查的好友电话是哪位好友呢"
            },
            {
                "user": "小明",
                "state": "查找联系人(联系人=小明) THEN 打电话(设备类型=None, 电话卡=移动卡, 电话号码=[ToFill], 联系人=小明)",
                "assistant": null
            }
        ]
    },
    {
        "history": [
            {
                "user": "请帮我接通一下小强的语音通话，接听之后再查找一下号码并打给他用我的电信卡",
                "state": "启动社交应用程序通话(联系人=小强, 通话模式=语音通话, 应用名称=None) AND 查找联系人(联系人=None) THEN 打电话(设备类型=None, 电话卡=电信卡, 电话号码=[ToFill], 联系人=None)",
                "assistant": "为您成功接通一下小强的语音通话，帮您搜索哪位好友的电话号码呢"
            },
            {
                "user": "小芳",
                "state": "查找联系人(联系人=小芳) THEN 打电话(设备类型=None, 电话卡=电信卡, 电话号码=[ToFill], 联系人=小芳)",
                "assistant": null
            }
        ]
    },
    {
        "history": [
            {
                "user": "帮我接通小华的语音通话，帮我搜索电话并用移动卡打电话给她",
                "state": "启动社交应用程序通话(联系人=小华, 通话模式=语音通话, 应用名称=None) AND 查找联系人(联系人=None) THEN 打电话(设备类型=None, 电话卡=移动卡, 电话号码=[ToFill], 联系人=None)",
                "assistant": "成功接通小华的语音通话，您需要查找哪位好友电话呢"
            },
            {
                "user": "小杰",
                "state": "查找联系人(联系人=小杰) THEN 打电话(设备类型=None, 电话卡=移动卡, 电话号码=[ToFill], 联系人=小杰)",
                "assistant": null
            }
        ]
    },
    {
        "history": [
            {
                "user": "帮我接通张三的语音通话，再帮我搜索出好友电话并用联通卡打电话给他",
                "state": "启动社交应用程序通话(联系人=张三, 通话模式=语音通话, 应用名称=None) AND 查找联系人(联系人=None) THEN 打电话(设备类型=None, 电话卡=联通卡, 电话号码=[ToFill], 联系人=None)",
                "assistant": "为您成功接通张三的语音通话，您需要查的好友电话是哪位好友呢"
            },
            {
                "user": "李四",
                "state": "启动社交应用程序通话(联系人=张三, 通话模式=语音通话, 应用名称=None) AND 查找联系人(联系人=李四) THEN 打电话(设备类型=None, 电话卡=联通卡, 电话号码=[ToFill], 联系人=None)",
                "assistant": null
            }
        ]
    },
    {
        "history": [
            {
                "user": "帮我给王五打一个语音通话，之后再查找一下号码并用我的电信卡打电话给他",
                "state": "启动社交应用程序通话(联系人=王五, 通话模式=语音通话, 应用名称=None) AND 查找联系人(联系人=None) THEN 打电话(设备类型=None, 电话卡=电信卡, 电话号码=[ToFill], 联系人=None)",
                "assistant": "为您成功拨打王五的语音通话，帮您搜索电话号码的好友是谁呢"
            },
            {
                "user": "赵六",
                "state": "查找联系人(联系人=赵六) THEN 打电话(设备类型=None, 电话卡=电信卡, 电话号码=[ToFill], 联系人=赵六)",
                "assistant": null
            }
        ]
    },
    {
        "history": [
            {
                "user": "帮我接通小红的语音通话，搜索出好友电话并用移动卡打电话给这位好友",
                "state": "启动社交应用程序通话(联系人=小红, 通话模式=语音通话, 应用名称=None) AND 查找联系人(联系人=None) THEN 打电话(设备类型=None, 电话卡=移动卡, 电话号码=[ToFill], 联系人=None)",
                "assistant": "为您成功接通小红的语音通话，您需要查的好友电话是哪位好友呢"
            },
            {
                "user": "小明",
                "state": "查找联系人(联系人=小明) THEN 打电话(设备类型=None, 电话卡=移动卡, 电话号码=[ToFill], 联系人=小明)",
                "assistant": null
            }
        ]
    },
    {
        "history": [
            {
                "user": "请帮我接通一下小刚的语音通话，接听之后再查找一下号码并打给他用我的电信卡",
                "state": "启动社交应用程序通话(联系人=小刚, 通话模式=语音通话, 应用名称=None) AND 查找联系人(联系人=None) THEN 打电话(设备类型=None, 电话卡=电信卡, 电话号码=[ToFill], 联系人=None)",
                "assistant": "为您成功接通一下小刚的语音通话，帮您搜索哪位好友的电话号码呢"
            },
            {
                "user": "小丽",
                "state": "查找联系人(联系人=小丽) THEN 打电话(设备类型=None, 电话卡=电信卡, 电话号码=[ToFill], 联系人=小丽)",
                "assistant": null
            }
        ]
    },
    {
        "history": [
            {
                "user": "帮我接通小芳的语音通话，帮我搜索电话并用移动卡打电话给她",
                "state": "启动社交应用程序通话(联系人=小芳, 通话模式=语音通话, 应用名称=None) AND 查找联系人(联系人=None) THEN 打电话(设备类型=None, 电话卡=移动卡, 电话号码=[ToFill], 联系人=None)",
                "assistant": "成功接通小芳的语音通话，您需要查找哪位好友电话呢"
            },
            {
                "user": "小强",
                "state": "查找联系人(联系人=小强) THEN 打电话(设备类型=None, 电话卡=移动卡, 电话号码=[ToFill], 联系人=小强)",
                "assistant": null
            }
        ]
    },
    {
        "history": [
            {
                "user": "帮我接通小李的语音通话，再帮我搜索出好友电话并用联通卡打电话给他",
                "state": "启动社交应用程序通话(联系人=小李, 通话模式=语音通话, 应用名称=None) AND 查找联系人(联系人=None) THEN 打电话(设备类型=None, 电话卡=联通卡, 电话号码=[ToFill], 联系人=None)",
                "assistant": "为您成功接通小李的语音通话，您需要查的好友电话是哪位好友呢"
            },
            {
                "user": "小王",
                "state": "启动社交应用程序通话(联系人=小李, 通话模式=语音通话, 应用名称=None) AND 查找联系人(联系人=小王) THEN 打电话(设备类型=None, 电话卡=联通卡, 电话号码=[ToFill], 联系人=None)",
                "assistant": null
            }
        ]
    },
    {
        "history": [
            {
                "user": "帮我给小张打一个语音通话，之后再查找一下号码并用我的电信卡打电话给他",
                "state": "启动社交应用程序通话(联系人=小张, 通话模式=语音通话, 应用名称=None) AND 查找联系人(联系人=None) THEN 打电话(设备类型=None, 电话卡=电信卡, 电话号码=[ToFill], 联系人=None)",
                "assistant": "为您成功拨打小张的语音通话，帮您搜索电话号码的好友是谁呢"
            },
            {
                "user": "小赵",
                "state": "查找联系人(联系人=小赵) THEN 打电话(设备类型=None, 电话卡=电信卡, 电话号码=[ToFill], 联系人=小赵)",
                "assistant": null
            }
        ]
    },
    {
        "history": [
            {
                "user": "帮我接通小刘的语音通话，搜索出好友电话并用移动卡打电话给这位好友",
                "state": "启动社交应用程序通话(联系人=小刘, 通话模式=语音通话, 应用名称=None) AND 查找联系人(联系人=None) THEN 打电话(设备类型=None, 电话卡=移动卡, 电话号码=[ToFill], 联系人=None)",
                "assistant": "为您成功接通小刘的语音通话，您需要查的好友电话是哪位好友呢"
            },
            {
                "user": "小陈",
                "state": "查找联系人(联系人=小陈) THEN 打电话(设备类型=None, 电话卡=移动卡, 电话号码=[ToFill], 联系人=小陈)",
                "assistant": null
            }
        ]
    },
    {
        "history": [
            {
                "user": "请帮我接通一下小吴的语音通话，接听之后再查找一下号码并打给他用我的电信卡",
                "state": "启动社交应用程序通话(联系人=小吴, 通话模式=语音通话, 应用名称=None) AND 查找联系人(联系人=None) THEN 打电话(设备类型=None, 电话卡=电信卡, 电话号码=[ToFill], 联系人=None)",
                "assistant": "为您成功接通一下小吴的语音通话，帮您搜索哪位好友的电话号码呢"
            },
            {
                "user": "小周",
                "state": "查找联系人(联系人=小周) THEN 打电话(设备类型=None, 电话卡=电信卡, 电话号码=[ToFill], 联系人=小周)",
                "assistant": null
            }
        ]
    },
    {
        "history": [
            {
                "user": "帮我接通小郑的语音通话，帮我搜索电话并用移动卡打电话给她",
                "state": "启动社交应用程序通话(联系人=小郑, 通话模式=语音通话, 应用名称=None) AND 查找联系人(联系人=None) THEN 打电话(设备类型=None, 电话卡=移动卡, 电话号码=[ToFill], 联系人=None)",
                "assistant": "成功接通小郑的语音通话，您需要查找哪位好友电话呢"
            },
            {
                "user": "小孙",
                "state": "查找联系人(联系人=小孙) THEN 打电话(设备类型=None, 电话卡=移动卡, 电话号码=[ToFill], 联系人=小孙)",
                "assistant": null
            }
        ]
    },
    {
        "history": [
            {
                "user": "帮我接通张三的语音通话，再帮我搜索出好友电话并用联通卡打电话给他",
                "state": "启动社交应用程序通话(联系人=张三, 通话模式=语音通话, 应用名称=None) AND 查找联系人(联系人=None) THEN 打电话(设备类型=None, 电话卡=联通卡, 电话号码=[ToFill], 联系人=None)",
                "assistant": "为您成功接通张三的语音通话，您需要查的好友电话是哪位好友呢"
            },
            {
                "user": "李四",
                "state": "查找联系人(联系人=李四) THEN 打电话(设备类型=None, 电话卡=联通卡, 电话号码=[ToFill], 联系人=李四)",
                "assistant": null
            }
        ]
    },
    {
        "history": [
            {
                "user": "帮我给王五打一个语音通话，之后再查找一下号码并用我的电信卡打电话给他",
                "state": "启动社交应用程序通话(联系人=王五, 通话模式=语音通话, 应用名称=None) AND 查找联系人(联系人=None) THEN 打电话(设备类型=None, 电话卡=电信卡, 电话号码=[ToFill], 联系人=None)",
                "assistant": "为您成功拨打王五的语音通话，帮您搜索电话号码的好友是谁呢"
            },
            {
                "user": "赵六",
                "state": "查找联系人(联系人=赵六) THEN 打电话(设备类型=None, 电话卡=电信卡, 电话号码=[ToFill], 联系人=赵六)",
                "assistant": null
            }
        ]
    },
    {
        "history": [
            {
                "user": "帮我接通小红的语音通话，搜索出好友电话并用移动卡打电话给这位好友",
                "state": "启动社交应用程序通话(联系人=小红, 通话模式=语音通话, 应用名称=None) AND 查找联系人(联系人=None) THEN 打电话(设备类型=None, 电话卡=移动卡, 电话号码=[ToFill], 联系人=None)",
                "assistant": "为您成功接通小红的语音通话，您需要查的好友电话是哪位好友呢"
            },
            {
                "user": "小明",
                "state": "查找联系人(联系人=小明) THEN 打电话(设备类型=None, 电话卡=移动卡, 电话号码=[ToFill], 联系人=小明)",
                "assistant": null
            }
        ]
    },
    {
        "history": [
            {
                "user": "请帮我接通一下小刚的语音通话，接听之后再查找一下号码并打给他用我的电信卡",
                "state": "启动社交应用程序通话(联系人=小刚, 通话模式=语音通话, 应用名称=None) AND 查找联系人(联系人=None) THEN 打电话(设备类型=None, 电话卡=电信卡, 电话号码=[ToFill], 联系人=None)",
                "assistant": "为您成功接通一下小刚的语音通话，帮您搜索哪位好友的电话号码呢"
            },
            {
                "user": "小丽",
                "state": "查找联系人(联系人=小丽) THEN 打电话(设备类型=None, 电话卡=电信卡, 电话号码=[ToFill], 联系人=小丽)",
                "assistant": null
            }
        ]
    },
    {
        "history": [
            {
                "user": "帮我接通小芳的语音通话，帮我搜索电话并用移动卡打电话给她",
                "state": "启动社交应用程序通话(联系人=小芳, 通话模式=语音通话, 应用名称=None) AND 查找联系人(联系人=None) THEN 打电话(设备类型=None, 电话卡=移动卡, 电话号码=[ToFill], 联系人=None)",
                "assistant": "成功接通小芳的语音通话，您需要查找哪位好友电话呢"
            },
            {
                "user": "小强",
                "state": "查找联系人(联系人=小强) THEN 打电话(设备类型=None, 电话卡=移动卡, 电话号码=[ToFill], 联系人=小强)",
                "assistant": null
            }
        ]
    },
    {
        "history": [
            {
                "user": "帮我接通小美的语音通话，再帮我搜索出好友电话并用联通卡打电话给她",
                "state": "启动社交应用程序通话(联系人=小美, 通话模式=语音通话, 应用名称=None) AND 查找联系人(联系人=None) THEN 打电话(设备类型=None, 电话卡=联通卡, 电话号码=[ToFill], 联系人=None)",
                "assistant": "为您成功接通小美的语音通话，您需要查的好友电话是哪位好友呢"
            },
            {
                "user": "小华",
                "state": "查找联系人(联系人=小华) THEN 打电话(设备类型=None, 电话卡=联通卡, 电话号码=[ToFill], 联系人=小华)",
                "assistant": null
            }
        ]
    },
    {
        "history": [
            {
                "user": "帮我给小杰打一个语音通话，之后再查找一下号码并用我的电信卡打电话给他",
                "state": "启动社交应用程序通话(联系人=小杰, 通话模式=语音通话, 应用名称=None) AND 查找联系人(联系人=None) THEN 打电话(设备类型=None, 电话卡=电信卡, 电话号码=[ToFill], 联系人=None)",
                "assistant": "为您成功拨打小杰的语音通话，帮您搜索电话号码的好友是谁呢"
            },
            {
                "user": "小丽",
                "state": "查找联系人(联系人=小丽) THEN 打电话(设备类型=None, 电话卡=电信卡, 电话号码=[ToFill], 联系人=小丽)",
                "assistant": null
            }
        ]
    },
    {
        "history": [
            {
                "user": "帮我接通小丽的语音通话，搜索出好友电话并用移动卡打电话给这位好友",
                "state": "启动社交应用程序通话(联系人=小丽, 通话模式=语音通话, 应用名称=None) AND 查找联系人(联系人=None) THEN 打电话(设备类型=None, 电话卡=移动卡, 电话号码=[ToFill], 联系人=None)",
                "assistant": "为您成功接通小丽的语音通话，您需要查的好友电话是哪位好友呢"
            },
            {
                "user": "小明",
                "state": "查找联系人(联系人=小明) THEN 打电话(设备类型=None, 电话卡=移动卡, 电话号码=[ToFill], 联系人=小明)",
                "assistant": null
            }
        ]
    },
    {
        "history": [
            {
                "user": "请帮我接通一下小强的语音通话，接听之后再查找一下号码并打给他用我的电信卡",
                "state": "启动社交应用程序通话(联系人=小强, 通话模式=语音通话, 应用名称=None) AND 查找联系人(联系人=None) THEN 打电话(设备类型=None, 电话卡=电信卡, 电话号码=[ToFill], 联系人=None)",
                "assistant": "为您成功接通一下小强的语音通话，帮您搜索哪位好友的电话号码呢"
            },
            {
                "user": "小芳",
                "state": "查找联系人(联系人=小芳) THEN 打电话(设备类型=None, 电话卡=电信卡, 电话号码=[ToFill], 联系人=小芳)",
                "assistant": null
            }
        ]
    },
    {
        "history": [
            {
                "user": "帮我接通小华的语音通话，帮我搜索电话并用移动卡打电话给她",
                "state": "启动社交应用程序通话(联系人=小华, 通话模式=语音通话, 应用名称=None) AND 查找联系人(联系人=None) THEN 打电话(设备类型=None, 电话卡=移动卡, 电话号码=[ToFill], 联系人=None)",
                "assistant": "成功接通小华的语音通话，您需要查找哪位好友电话呢"
            },
            {
                "user": "小杰",
                "state": "查找联系人(联系人=小杰) THEN 打电话(设备类型=None, 电话卡=移动卡, 电话号码=[ToFill], 联系人=小杰)",
                "assistant": null
            }
        ]
    },
    {
        "history": [
            {
                "user": "帮我接通张三的语音通话，再帮我搜索出好友电话并用联通卡打电话给他",
                "state": "启动社交应用程序通话(联系人=张三, 通话模式=语音通话, 应用名称=None) AND 查找联系人(联系人=None) THEN 打电话(设备类型=None, 电话卡=联通卡, 电话号码=[ToFill], 联系人=None)",
                "assistant": "为您成功接通张三的语音通话，您需要查的好友电话是哪位好友呢"
            },
            {
                "user": "李四",
                "state": "启动社交应用程序通话(联系人=张三, 通话模式=语音通话, 应用名称=None) AND 查找联系人(联系人=李四) THEN 打电话(设备类型=None, 电话卡=联通卡, 电话号码=[ToFill], 联系人=None)",
                "assistant": null
            }
        ]
    },
    {
        "history": [
            {
                "user": "帮我给王五打一个语音通话，之后再查找一下号码并用我的电信卡打电话给他",
                "state": "启动社交应用程序通话(联系人=王五, 通话模式=语音通话, 应用名称=None) AND 查找联系人(联系人=None) THEN 打电话(设备类型=None, 电话卡=电信卡, 电话号码=[ToFill], 联系人=None)",
                "assistant": "为您成功拨打王五的语音通话，帮您搜索电话号码的好友是谁呢"
            },
            {
                "user": "赵六",
                "state": "查找联系人(联系人=赵六) THEN 打电话(设备类型=None, 电话卡=电信卡, 电话号码=[ToFill], 联系人=赵六)",
                "assistant": null
            }
        ]
    },
    {
        "history": [
            {
                "user": "帮我接通小红的语音通话，搜索出好友电话并用移动卡打电话给这位好友",
                "state": "启动社交应用程序通话(联系人=小红, 通话模式=语音通话, 应用名称=None) AND 查找联系人(联系人=None) THEN 打电话(设备类型=None, 电话卡=移动卡, 电话号码=[ToFill], 联系人=None)",
                "assistant": "为您成功接通小红的语音通话，您需要查的好友电话是哪位好友呢"
            },
            {
                "user": "小明",
                "state": "查找联系人(联系人=小明) THEN 打电话(设备类型=None, 电话卡=移动卡, 电话号码=[ToFill], 联系人=小明)",
                "assistant": null
            }
        ]
    },
    {
        "history": [
            {
                "user": "请帮我接通一下小李的语音通话，接听之后再查找一下号码并打给她用我的电信卡",
                "state": "启动社交应用程序通话(联系人=小李, 通话模式=语音通话, 应用名称=None) AND 查找联系人(联系人=None) THEN 打电话(设备类型=None, 电话卡=电信卡, 电话号码=[ToFill], 联系人=None)",
                "assistant": "为您成功接通一下小李的语音通话，帮您搜索哪位好友的电话号码呢"
            },
            {
                "user": "小张",
                "state": "查找联系人(联系人=小张) THEN 打电话(设备类型=None, 电话卡=电信卡, 电话号码=[ToFill], 联系人=小张)",
                "assistant": null
            }
        ]
    },
    {
        "history": [
            {
                "user": "帮我接通小王的语音通话，帮我搜索电话并用移动卡打电话给她",
                "state": "启动社交应用程序通话(联系人=小王, 通话模式=语音通话, 应用名称=None) AND 查找联系人(联系人=None) THEN 打电话(设备类型=None, 电话卡=移动卡, 电话号码=[ToFill], 联系人=None)",
                "assistant": "成功接通小王的语音通话，您需要查找哪位好友电话呢"
            },
            {
                "user": "小刘",
                "state": "查找联系人(联系人=小刘) THEN 打电话(设备类型=None, 电话卡=移动卡, 电话号码=[ToFill], 联系人=小刘)",
                "assistant": null
            }
        ]
    },
    {
        "history": [
            {
                "user": "帮我接通小陈的语音通话，再帮我搜索出好友电话并用联通卡打电话给他",
                "state": "启动社交应用程序通话(联系人=小陈, 通话模式=语音通话, 应用名称=None) AND 查找联系人(联系人=None) THEN 打电话(设备类型=None, 电话卡=联通卡, 电话号码=[ToFill], 联系人=None)",
                "assistant": "为您成功接通小陈的语音通话，您需要查的好友电话是哪位好友呢"
            },
            {
                "user": "小赵",
                "state": "启动社交应用程序通话(联系人=小陈, 通话模式=语音通话, 应用名称=None) AND 查找联系人(联系人=小赵) THEN 打电话(设备类型=None, 电话卡=联通卡, 电话号码=[ToFill], 联系人=None)",
                "assistant": null
            }
        ]
    },
    {
        "history": [
            {
                "user": "帮我给小杨打一个语音通话，之后再查找一下号码并用我的电信卡打电话给他",
                "state": "启动社交应用程序通话(联系人=小杨, 通话模式=语音通话, 应用名称=None) AND 查找联系人(联系人=None) THEN 打电话(设备类型=None, 电话卡=电信卡, 电话号码=[ToFill], 联系人=None)",
                "assistant": "为您成功拨打小杨的语音通话，帮您搜索电话号码的好友是谁呢"
            },
            {
                "user": "小吴",
                "state": "查找联系人(联系人=小吴) THEN 打电话(设备类型=None, 电话卡=电信卡, 电话号码=[ToFill], 联系人=小吴)",
                "assistant": null
            }
        ]
    },
    {
        "history": [
            {
                "user": "帮我接通小周的语音通话，搜索出好友电话并用移动卡打电话给这位好友",
                "state": "启动社交应用程序通话(联系人=小周, 通话模式=语音通话, 应用名称=None) AND 查找联系人(联系人=None) THEN 打电话(设备类型=None, 电话卡=移动卡, 电话号码=[ToFill], 联系人=None)",
                "assistant": "为您成功接通小周的语音通话，您需要查的好友电话是哪位好友呢"
            },
            {
                "user": "小郑",
                "state": "查找联系人(联系人=小郑) THEN 打电话(设备类型=None, 电话卡=移动卡, 电话号码=[ToFill], 联系人=小郑)",
                "assistant": null
            }
        ]
    },
    {
        "history": [
            {
                "user": "请帮我接通一下小孙的语音通话，接听之后再查找一下号码并打给她用我的电信卡",
                "state": "启动社交应用程序通话(联系人=小孙, 通话模式=语音通话, 应用名称=None) AND 查找联系人(联系人=None) THEN 打电话(设备类型=None, 电话卡=电信卡, 电话号码=[ToFill], 联系人=None)",
                "assistant": "为您成功接通一下小孙的语音通话，帮您搜索哪位好友的电话号码呢"
            },
            {
                "user": "小钱",
                "state": "查找联系人(联系人=小钱) THEN 打电话(设备类型=None, 电话卡=电信卡, 电话号码=[ToFill], 联系人=小钱)",
                "assistant": null
            }
        ]
    },
    {
        "history": [
            {
                "user": "帮我接通小吴的语音通话，帮我搜索电话并用移动卡打电话给她",
                "state": "启动社交应用程序通话(联系人=小吴, 通话模式=语音通话, 应用名称=None) AND 查找联系人(联系人=None) THEN 打电话(设备类型=None, 电话卡=移动卡, 电话号码=[ToFill], 联系人=None)",
                "assistant": "成功接通小吴的语音通话，您需要查找哪位好友电话呢"
            },
            {
                "user": "小李",
                "state": "查找联系人(联系人=小李) THEN 打电话(设备类型=None, 电话卡=移动卡, 电话号码=[ToFill], 联系人=小李)",
                "assistant": null
            }
        ]
    },
    {
        "history": [
            {
                "user": "帮我接通李三欧的语音通话，再帮我搜索出朋友电话并用电信卡打电话给她",
                "state": "启动社交应用程序通话(联系人=李三欧, 通话模式=语音通话, 应用名称=None) AND 查找联系人(联系人=None) THEN 打电话(设备类型=None, 电话卡=电信卡, 电话号码=[ToFill], 联系人=None)",
                "assistant": "为您成功打开于李三欧的语音通话，请问需要搜索的是哪位好友的电话号码呢"
            },
            {
                "user": "二狗",
                "state": "查找联系人(联系人=二狗) THEN 打电话(设备类型=None, 电话卡=电信卡, 电话号码=[ToFill], 联系人=二狗)",
                "assistant": null
            }
        ]
    },
    {
        "history": [
            {
                "user": "帮我接通航仔的视频通话，接完之后帮我搜索好友电话号码，并用联通卡打电话给好友",
                "state": "启动社交应用程序通话(联系人=航仔, 通话模式=视频通话, 应用名称=None) AND 查找联系人(联系人=None) THEN 打电话(设备类型=None, 电话卡=联通卡, 电话号码=[ToFill], 联系人=None)",
                "assistant": "已成功帮您接通视频，请问帮您查找哪位好友的电话号码呢"
            },
            {
                "user": "珍祝",
                "state": "查找联系人(联系人=珍祝) THEN 打电话(设备类型=None, 电话卡=联通卡, 电话号码=[ToFill], 联系人=珍祝)",
                "assistant": null
            }
        ]
    },
    {
        "history": [
            {
                "user": "帮我接通李灿灿的语音通话，再帮我搜索出好友电话并用电信卡打电话给她",
                "state": "启动社交应用程序通话(联系人=李灿灿, 通话模式=语音通话, 应用名称=None) AND 查找联系人(联系人=None) THEN 打电话(设备类型=None, 电话卡=电信卡, 电话号码=[ToFill], 联系人=None)",
                "assistant": "为您成功接通李灿灿的语音通话，您需要查的好友电话是哪位好友呢"
            },
            {
                "user": "李二狗",
                "state": "启动社交应用程序通话(联系人=李灿灿, 通话模式=语音通话, 应用名称=None) AND 查找联系人(联系人=李二狗) THEN 打电话(设备类型=None, 电话卡=电信卡, 电话号码=[ToFill], 联系人=None)",
                "assistant": null
            }
        ]
    },
    {
        "history": [
            {
                "user": "帮我接通娜比的语音通话，搜索出好友电话并用移动卡打电话给这位好友",
                "state": "启动社交应用程序通话(联系人=娜比, 通话模式=语音通话, 应用名称=None) AND 查找联系人(联系人=None) THEN 打电话(设备类型=None, 电话卡=移动卡, 电话号码=[ToFill], 联系人=None)",
                "assistant": "为您成功接通娜比的语音通话，您需要查的好友电话是哪位好友呢"
            },
            {
                "user": "李圈",
                "state": "查找联系人(联系人=李圈) THEN 打电话(设备类型=None, 电话卡=移动卡, 电话号码=[ToFill], 联系人=李圈)",
                "assistant": null
            }
        ]
    },
    {
        "history": [
            {
                "user": "帮我接通轩仔的语音通话，帮我搜索电话并用移动卡打电话给她",
                "state": "启动社交应用程序通话(联系人=轩仔, 通话模式=语音通话, 应用名称=None) AND 查找联系人(联系人=None) THEN 打电话(设备类型=None, 电话卡=移动卡, 电话号码=[ToFill], 联系人=None)",
                "assistant": "成功接通轩仔的语音通话，您需要查找哪位好友电话呢"
            },
            {
                "user": "彩华",
                "state": "查找联系人(联系人=彩华) THEN 打电话(设备类型=None, 电话卡=移动卡, 电话号码=[ToFill], 联系人=彩华)",
                "assistant": null
            }
        ]
    },
    {
        "history": [
            {
                "user": "请帮我接通一下小菊的语音通话，接听之后再查找一下号码并打给她用我的电信卡",
                "state": "启动社交应用程序通话(联系人=小菊, 通话模式=语音通话, 应用名称=None) AND 查找联系人(联系人=None) THEN 打电话(设备类型=None, 电话卡=电信卡, 电话号码=[ToFill], 联系人=None)",
                "assistant": "为您成功接通一下小菊的语音通话，帮您搜索哪位好友的电话号码呢"
            },
            {
                "user": "小蓝",
                "state": "查找联系人(联系人=小蓝) THEN 打电话(设备类型=None, 电话卡=电信卡, 电话号码=[ToFill], 联系人=小蓝)",
                "assistant": null
            }
        ]
    },
    {
        "history": [
            {
                "user": "帮我给花湖打一个语音通话，之后再查找一下号码并用我的移动卡打电话给他",
                "state": "启动社交应用程序通话(联系人=花湖, 通话模式=语音通话, 应用名称=None) AND 查找联系人(联系人=None) THEN 打电话(设备类型=None, 电话卡=移动卡, 电话号码=[ToFill], 联系人=None)",
                "assistant": "为您成功拨打花湖的语音通话，帮您搜索电话号码的好友是谁呢"
            },
            {
                "user": "坎墩",
                "state": "查找联系人(联系人=坎墩) THEN 打电话(设备类型=None, 电话卡=移动卡, 电话号码=[ToFill], 联系人=坎墩)",
                "assistant": null
            }
        ]
    },
    {
        "history": [
            {
                "user": "帮我给彩虹打一个视频通话，之后再查找一下号码，用我的联通卡拨打回去",
                "state": "启动社交应用程序通话(联系人=彩虹, 通话模式=视频通话, 应用名称=None) AND 查找联系人(联系人=None) THEN 打电话(设备类型=None, 电话卡=联通卡, 电话号码=[ToFill], 联系人=None)",
                "assistant": "成功为您拨打彩虹的视频通话，帮您查号码的联系人是谁呢"
            },
            {
                "user": "小马",
                "state": "查找联系人(联系人=小马) THEN 打电话(设备类型=None, 电话卡=联通卡, 电话号码=[ToFill], 联系人=小马)",
                "assistant": null
            }
        ]
    },
    {
        "history": [
            {
                "user": "帮我接通我的朋友包子打给我的视频通话，再帮我查找肆意的电话并用我的移动卡号码打给她",
                "state": "启动社交应用程序通话(联系人=包子, 通话模式=视频通话, 应用名称=None) AND 查找联系人(联系人=None) THEN 打电话(设备类型=None, 电话卡=移动卡, 电话号码=[ToFill], 联系人=None)",
                "assistant": "成功为您接通视频通话，帮您搜索电话号码的好友是谁呢?"
            },
            {
                "user": "肆意",
                "state": "查找联系人(联系人=None) THEN 打电话(设备类型=None, 电话卡=移动卡, 电话号码=[ToFill], 联系人=None)",
                "assistant": null
            }
        ]
    }
]